{"gt": 6, "dollar": 4, "month": 3, "four": 1, "474,270": 1, "ga": 3, "1,295,104": 1, "mill": 1, "compani": 18, "harvest": 1, "midseason": 2, "young": 4, "metromail": 1, "sarney": 2, "deficit": 1, "3,495,579": 1, "sourc": 1, "fall": 1, "level": 1, "33,453": 1, "adjust": 2, "3,038,000": 1, "div": 2, "natur": 1, "crop": 1, "sign": 1, "rate": 1, "durkin": 1, "proxi": 2, "compar": 1, "new": 1, "net": 10, "demarku": 1, "full": 1, "pacif": 4, "gener": 1, "agreement": 1, "414,890": 1, "china": 1, "valu": 1, "128,164": 1, "237,859": 1, "newmont": 1, "30": 2, "technolog": 3, "36": 1, "prior": 4, "taft": 2, "depart": 1, "total": 1, "establish": 1, "market": 7, "5,747,000": 1, "would": 1, "&": 9, "petroleum": 2, "two": 2, "133,119": 1, "uss": 1, "ip": 1, "flat": 1, "``": 5, "cumul": 1, "ventur": 1, "95": 1, "none": 9, "hous": 1, "nine": 2, "496,391": 1, "meet": 1, "purpos": 2, "control": 2, "reynold": 2, "share": 13, "council": 1, "mi-tech": 1, "avg": 3, "end": 1, "winter": 1, "reuter": 11, "delay": 1, "negoti": 1, "stock": 2, "plant": 3, "de": 1, "reduc": 1, "may": 1, "chines": 1, "presid": 2, "southern": 3, "fe": 4, "bloom": 1, "parallel": 2, "short": 1, "1,321,940": 1, "japanes": 1, "exclud": 3, "coal": 1, "mainten": 1, "talk": 3, "478,991": 1, "six": 3, "offici": 2, "approv": 4, "becaus": 1, "trade": 6, "report": 1, "japan": 2, "dividend": 1, "24": 2, "divis": 4, "27": 4, "group": 10, "21": 2, "22": 1, "4,142,000": 1, "28": 3, ",": 75, "pct": 9, "lt": 8, "nakason": 1, "shr": 11, "nation": 2, "nov": 1, "investor": 1, "hall": 1, "bank": 2, "clercq": 2, "1.05": 1, "name": 1, "opec": 1, "februari": 4, "januari": 3, "quarter": 2, "737,917": 1, "vamga": 1, "hsla": 2, "ec": 1, "h-pile": 3, "expect": 2, "year": 12, "80": 1, "202,500": 1, "20.7": 1, "profit": 6, "rev": 7, "1.75": 1, "shipment": 1, "venezuela": 1, "641,000": 1, "earlier": 5, "bass": 2, "u.s.": 2, "infin": 1, "releas": 1, "florida": 1, "1,069,550": 1, "american": 2, "ltd": 3, "audio/video": 1, "oper": 7, "major": 1, "4,793,000": 1, "one": 1, "784,000": 1, "acquisit": 3, "agre": 1, "facil": 1, "bilzerian": 1, "capac": 3, "station": 1, "ton": 2, "1,329,000": 1, "low": 2, "shell": 1, "season": 1, "pari": 1, "part": 1, "369,848": 1, "90.25": 1, "steel": 5, "10": 2, "13": 1, ":": 1, "15": 4, "14": 1, "project": 2, "273": 1, "balanc": 3, "1985/86": 1, "arkla": 3, "partnership": 2, "mine": 1, "tonight": 1, "seed": 1, "deliv": 1, "seek": 1, "semi-finish": 2, "-": 1, "760,603": 1, "note": 1, "also": 3, "sh": 1, "build": 4, "unemploy": 1, "miyazawa": 1, "pipelin": 4, "3,785,607": 1, "price": 9, "quota": 3, "eight": 3, "plan": 4, "letter": 1, "79": 2, "841,908": 1, "grove": 1, "sale": 1, "declar": 1, "1,054,000": 1, "barrel": 3, "dot": 2, "gold": 1, "show": 1, "randol": 1, "texa": 2, "despit": 1, "onli": 1, "treasuri": 1, "merger": 1, "transact": 1, "figur": 1, "sugar": 2, "fuel": 2, "8": 1, "discontinu": 2, "893,612": 1, "plate": 2, "orang": 1, "59,520": 1, "12": 1, "import": 5, "increas": 4, "sunni": 1, ";": 17, "earn": 2, "bar": 1, "synthet": 1, "147,671": 1, "90": 1, "qtr": 2, "brazil": 2, "said": 60, "dlr": 27, "state": 2, "outstand": 1, "crude": 4, "progress": 2, "attribut": 1, "altern": 1, "accord": 2, "wa": 7, "25": 2, "sold": 1, "20": 2, "mitsui": 1, "last": 1, "4,212,000": 1, "7,500,000": 1, "foreign": 2, "april": 3, "comdata": 1, "mani": 1, "co": 2, "cyclop": 2, "non-perform": 1, "tonn": 1, "65": 1, "shutdown": 1, "carbon": 1, "trust": 1, "ct": 19, "340,210": 1, "three": 1, ".": 1, "bolivar": 2, "revenu": 1, "interest": 1, "board": 1, "firm": 1, "stillmann": 1, "1,944,627": 1, "136,918": 1, "5,115,456": 1, "4,582,260": 1, "408,031": 1, "canadian": 2, "mln": 17, "employ": 1, "cvg": 1, "p.": 2, "refineri": 2, "pound": 3, "sugarcan": 1, "worldwid": 1, "rio": 1, "vs": 18, "substanti": 1, "henley": 2, "woodsid": 1, "develop": 1, "author": 1, "11.4": 1, "pay": 4, "split": 1, "grand": 2, "pak": 3, "week": 2, "oil": 10, "fiscal": 1, "nil": 1, "effect": 1, "rain": 1, "rais": 1, "chas.": 1, "refin": 3, "46": 1, "expens": 1, "propos": 1, "214": 1, "stake": 7, "year-on-year": 1, "product": 6, "penteco": 2, "ldp": 1, "elect": 2, "versu": 4, "324,011": 1, "rose": 1, "day": 1, "dixon": 3, "east": 2, "loan": 2, "smart": 1, "take": 1, "earli": 1, "...": 1, "royalti": 1, "march": 2, "temperatur": 1, "five": 1, "world": 2, "loss": 11, "bpd": 1, "qtli": 1, "54": 1, "shelf": 1, "manag": 1, "sharehold": 5, "111,210": 1, "3,904,373": 1, "per": 5, "estim": 1, "larg": 1, "unit": 7, "wheat": 2, "438,933": 1, "gencorp": 2, "corp": 3, "santa": 2, "offic": 1, "2,140,673": 1, "weather": 1, "1986": 5, "1987": 3, "1985": 2, "mcmillan": 1, "agricultur": 2, "start": 2, "includ": 2, "brazilian": 2, "valley": 3, "ago": 3, "north": 1, "reorgan": 1, "offer": 3, "subsidiari": 1, "frost": 1, "hi": 3, "gain": 2, "reef": 1, "10,100,000": 1, "ha": 5, "analyst": 4, "wish": 1, "smooth": 1, "olson": 1, "record": 4, "mth": 1, "limit": 1, "413,444": 1, "8,539,000": 1, "qtrli": 1, "352,000": 1, "''": 9, "257,157": 1, "cotton": 2, "areas.": 1, "107.1": 1, "45": 1, "field": 1, "4,010,000": 1, "'s": 13, "june": 1, "fell": 2, "520,200": 1, "'n": 2, "billion": 2, "invest": 2, "111.1": 1, "fresh": 2, "inc": 2}